pseudo_ecg/__init__.py
pseudo_ecg/ecg.py
pseudo_ecg-0.0.1.dist-info/LICENSE
pseudo_ecg-0.0.1.dist-info/METADATA
pseudo_ecg-0.0.1.dist-info/WHEEL
pseudo_ecg-0.0.1.dist-info/top_level.txt
pseudo_ecg-0.0.1.dist-info/RECORD
