Metadata-Version: 2.1
Name: pseudo-ecg
Version: 0.0.1
Summary: Library to compute pseudo ECG from bidomain and monodomain simulations
Author-email: Cécile Daversin-Catty <cecile@simula.no>, Henrik Finsberg <henriknf@simula.no>
License: Copyright 2023 Henrik Finsberg
License-File: LICENSE
Requires-Dist: numpy
Requires-Dist: scipy
Requires-Dist: tqdm
Provides-Extra: all
Requires-Dist: pseudo-ecg[test] ; extra == 'all'
Requires-Dist: pseudo-ecg[docs] ; extra == 'all'
Requires-Dist: pseudo-ecg[pypi] ; extra == 'all'
Requires-Dist: pseudo-ecg[dev] ; extra == 'all'
Provides-Extra: dev
Requires-Dist: pdbpp ; extra == 'dev'
Requires-Dist: ipython ; extra == 'dev'
Requires-Dist: bump2version ; extra == 'dev'
Requires-Dist: pre-commit ; extra == 'dev'
Provides-Extra: docs
Requires-Dist: jupyter-book ; extra == 'docs'
Provides-Extra: pypi
Requires-Dist: twine ; extra == 'pypi'
Requires-Dist: build ; extra == 'pypi'
Provides-Extra: test
Requires-Dist: pytest ; extra == 'test'
Requires-Dist: pytest-cov ; extra == 'test'
